tap_amazon_ads_dsp/__init__.py
tap_amazon_ads_dsp/client.py
tap_amazon_ads_dsp/discover.py
tap_amazon_ads_dsp/schema.py
tap_amazon_ads_dsp/sync.py
tap_amazon_ads_dsp/transform.py
tap_amazon_ads_dsp/schemas/audience.json
tap_amazon_ads_dsp/schemas/campaign.json
tap_amazon_ads_dsp/schemas/inventory.json
tap_amazon_ads_dsp/schemas/shared/common.json
tests/__init__.py
tests/configuration/__init__.py
tests/configuration/fixtures.py
tap_amazon_ads_dsp_velocity-0.0.9.dist-info/LICENSE
tap_amazon_ads_dsp_velocity-0.0.9.dist-info/METADATA
tap_amazon_ads_dsp_velocity-0.0.9.dist-info/WHEEL
tap_amazon_ads_dsp_velocity-0.0.9.dist-info/entry_points.txt
tap_amazon_ads_dsp_velocity-0.0.9.dist-info/top_level.txt
tap_amazon_ads_dsp_velocity-0.0.9.dist-info/RECORD
