Metadata-Version: 2.1
Name: tap-amazon-ads-dsp-velocity
Version: 0.0.9
Summary: Singer.io tap for extracting data from the Amazon Advertising DSP v1.0 API
Home-page: UNKNOWN
Author: scott.coleman@bytecode.io
License: UNKNOWN
Platform: UNKNOWN
Classifier: Programming Language :: Python :: 3 :: Only
Requires-Dist: backoff (==1.8.0)
Requires-Dist: requests (==2.23.0)
Requires-Dist: singer-python (==5.8.1)
Requires-Dist: requests-oauthlib (==1.3.0)
Provides-Extra: dev
Requires-Dist: pytest ; extra == 'dev'
Requires-Dist: requests-mock ; extra == 'dev'
